srtoffset/__init__.py
srtoffset/srtoffset.py
srtoffset-0.1.2.dist-info/entry_points.txt
srtoffset-0.1.2.dist-info/LICENSE
srtoffset-0.1.2.dist-info/WHEEL
srtoffset-0.1.2.dist-info/METADATA
srtoffset-0.1.2.dist-info/RECORD
