Metadata-Version: 2.1
Name: srtoffset
Version: 0.1.2
Summary: Apply a time offset to a subtitle .srt file
Home-page: https://github.com/brouberol/srtoffset
License: MIT
Author: Balthazar Rouberol
Author-email: br@imap.cc
Requires-Python: >=3.5,<4.0
Classifier: License :: OSI Approved :: MIT License
Classifier: Programming Language :: Python :: 3
Classifier: Programming Language :: Python :: 3.5
Classifier: Programming Language :: Python :: 3.6
Classifier: Programming Language :: Python :: 3.7
Classifier: Programming Language :: Python :: 3.8
Project-URL: Repository, https://github.com/brouberol/srtoffset
